aws_lambda_artifact_builder/__init__.py
aws_lambda_artifact_builder/_version.py
aws_lambda_artifact_builder/api.py
aws_lambda_artifact_builder/constants.py
aws_lambda_artifact_builder/imports.py
aws_lambda_artifact_builder/layer/__init__.py
aws_lambda_artifact_builder/layer/_build_lambda_layer_using_pip_in_container.py
aws_lambda_artifact_builder/layer/_build_lambda_layer_using_poetry_in_container.py
aws_lambda_artifact_builder/layer/_build_lambda_layer_using_uv_in_container.py
aws_lambda_artifact_builder/layer/builder.py
aws_lambda_artifact_builder/layer/foundation.py
aws_lambda_artifact_builder/layer/package.py
aws_lambda_artifact_builder/layer/pip_builder.py
aws_lambda_artifact_builder/layer/poetry_builder.py
aws_lambda_artifact_builder/layer/publish.py
aws_lambda_artifact_builder/layer/upload.py
aws_lambda_artifact_builder/layer/uv_builder.py
aws_lambda_artifact_builder/layer/workflow.py
aws_lambda_artifact_builder/paths.py
aws_lambda_artifact_builder/source.py
aws_lambda_artifact_builder/typehint.py
aws_lambda_artifact_builder/utils.py
aws_lambda_artifact_builder/vendor/__init__.py
aws_lambda_artifact_builder/vendor/better_pathlib.py
aws_lambda_artifact_builder/vendor/hashes.py
aws_lambda_artifact_builder/vendor/pytest_cov_helper.py
aws_lambda_artifact_builder/vendor/timer.py
aws_lambda_artifact_builder-0.1.8.dist-info/AUTHORS.rst
aws_lambda_artifact_builder-0.1.8.dist-info/LICENSE.txt
aws_lambda_artifact_builder-0.1.8.dist-info/METADATA
aws_lambda_artifact_builder-0.1.8.dist-info/WHEEL
aws_lambda_artifact_builder-0.1.8.dist-info/RECORD
